odoo/addons/portal_user_login_email_change/README.rst
odoo/addons/portal_user_login_email_change/__init__.py
odoo/addons/portal_user_login_email_change/__manifest__.py
odoo/addons/portal_user_login_email_change/i18n/portal_user_login_email_change.pot
odoo/addons/portal_user_login_email_change/models/__init__.py
odoo/addons/portal_user_login_email_change/models/res_partner.py
odoo/addons/portal_user_login_email_change/readme/CONTRIBUTORS.md
odoo/addons/portal_user_login_email_change/readme/DESCRIPTION.md
odoo/addons/portal_user_login_email_change/static/description/icon.png
odoo/addons/portal_user_login_email_change/static/description/index.html
odoo/addons/portal_user_login_email_change/tests/__init__.py
odoo/addons/portal_user_login_email_change/tests/test_portal_user_login_email_change.py
odoo_addon_portal_user_login_email_change-15.0.1.0.0.2.dist-info/METADATA
odoo_addon_portal_user_login_email_change-15.0.1.0.0.2.dist-info/WHEEL
odoo_addon_portal_user_login_email_change-15.0.1.0.0.2.dist-info/top_level.txt
odoo_addon_portal_user_login_email_change-15.0.1.0.0.2.dist-info/RECORD
